[{"__type__":"cc.SpriteFrame","content":{"name":"card11","texture":"b1K5NqJoZLK4CIcSxkOaQF","rect":[359,1430,117,151],"offset":[0,0],"originalSize":[117,151],"rotated":1}},{"__type__":"cc.SpriteFrame","content":{"name":"card08","texture":"b1K5NqJoZLK4CIcSxkOaQF","rect":[240,1532,117,151],"offset":[0,0],"originalSize":[117,151]}},{"__type__":"cc.SpriteFrame","content":{"name":"card42","texture":"b1K5NqJoZLK4CIcSxkOaQF","rect":[240,308,117,151],"offset":[0,0],"originalSize":[117,151]}},{"__type__":"cc.SpriteFrame","content":{"name":"card43","texture":"b1K5NqJoZLK4CIcSxkOaQF","rect":[121,308,117,151],"offset":[0,0],"originalSize":[117,151]}},{"__type__":"cc.SpriteFrame","content":{"name":"card18","texture":"b1K5NqJoZLK4CIcSxkOaQF","rect":[359,1073,117,151],"offset":[0,0],"originalSize":[117,151],"rotated":1}},{"__type__":"cc.SpriteFrame","content":{"name":"card49","texture":"b1K5NqJoZLK4CIcSxkOaQF","rect":[240,2,117,151],"offset":[0,0],"originalSize":[117,151]}},{"__type__":"cc.SpriteFrame","content":{"name":"card41","texture":"b1K5NqJoZLK4CIcSxkOaQF","rect":[359,359,117,151],"offset":[0,0],"originalSize":[117,151],"rotated":1}},{"__type__":"cc.SpriteFrame","content":{"name":"card07","texture":"b1K5NqJoZLK4CIcSxkOaQF","rect":[359,1549,117,151],"offset":[0,0],"originalSize":[117,151],"rotated":1}},{"__type__":"cc.SpriteFrame","content":{"name":"card30","texture":"b1K5NqJoZLK4CIcSxkOaQF","rect":[121,767,117,151],"offset":[0,0],"originalSize":[117,151]}},{"__type__":"cc.SpriteFrame","content":{"name":"card37","texture":"b1K5NqJoZLK4CIcSxkOaQF","rect":[359,478,117,151],"offset":[0,0],"originalSize":[117,151],"rotated":1}},{"__type__":"cc.SpriteFrame","content":{"name":"card01","texture":"b1K5NqJoZLK4CIcSxkOaQF","rect":[121,1838,117,151],"offset":[0,0],"originalSize":[117,151]}},{"__type__":"cc.SpriteFrame","content":{"name":"card29","texture":"b1K5NqJoZLK4CIcSxkOaQF","rect":[240,767,117,151],"offset":[0,0],"originalSize":[117,151]}},{"__type__":"cc.SpriteFrame","content":{"name":"card24","texture":"b1K5NqJoZLK4CIcSxkOaQF","rect":[359,954,117,151],"offset":[0,0],"originalSize":[117,151],"rotated":1}},{"__type__":"cc.SpriteFrame","content":{"name":"card06","texture":"b1K5NqJoZLK4CIcSxkOaQF","rect":[359,1668,117,151],"offset":[0,0],"originalSize":[117,151],"rotated":1}},{"__type__":"cc.SpriteFrame","content":{"name":"card14","texture":"b1K5NqJoZLK4CIcSxkOaQF","rect":[2,1532,117,151],"offset":[0,0],"originalSize":[117,151]}},{"__type__":"cc.SpriteFrame","content":{"name":"card23","texture":"b1K5NqJoZLK4CIcSxkOaQF","rect":[2,1226,117,151],"offset":[0,0],"originalSize":[117,151]}},{"__type__":"cc.SpriteFrame","content":{"name":"card19","texture":"b1K5NqJoZLK4CIcSxkOaQF","rect":[240,1073,117,151],"offset":[0,0],"originalSize":[117,151]}},{"__type__":"cc.SpriteFrame","content":{"name":"card10","texture":"b1K5NqJoZLK4CIcSxkOaQF","rect":[2,1685,117,151],"offset":[0,0],"originalSize":[117,151]}},{"__type__":"cc.SpriteFrame","content":{"name":"card04","texture":"b1K5NqJoZLK4CIcSxkOaQF","rect":[121,1685,117,151],"offset":[0,0],"originalSize":[117,151]}},{"__type__":"cc.SpriteFrame","content":{"name":"card20","texture":"b1K5NqJoZLK4CIcSxkOaQF","rect":[121,1226,117,151],"offset":[0,0],"originalSize":[117,151]}},{"__type__":"cc.SpriteFrame","content":{"name":"card50","texture":"b1K5NqJoZLK4CIcSxkOaQF","rect":[121,155,117,151],"offset":[0,0],"originalSize":[117,151]}},{"__type__":"cc.SpriteFrame","content":{"name":"card09","texture":"b1K5NqJoZLK4CIcSxkOaQF","rect":[121,1532,117,151],"offset":[0,0],"originalSize":[117,151]}},{"__type__":"cc.SpriteFrame","content":{"name":"card02","texture":"b1K5NqJoZLK4CIcSxkOaQF","rect":[359,1787,117,151],"offset":[0,0],"originalSize":[117,151],"rotated":1}},{"__type__":"cc.SpriteFrame","content":{"name":"card05","texture":"b1K5NqJoZLK4CIcSxkOaQF","rect":[2,1838,117,151],"offset":[0,0],"originalSize":[117,151]}},{"__type__":"cc.SpriteFrame","content":{"name":"card45","texture":"b1K5NqJoZLK4CIcSxkOaQF","rect":[359,240,117,151],"offset":[0,0],"originalSize":[117,151],"rotated":1}},{"__type__":"cc.SpriteFrame","content":{"name":"card38","texture":"b1K5NqJoZLK4CIcSxkOaQF","rect":[240,461,117,151],"offset":[0,0],"originalSize":[117,151]}},{"__type__":"cc.SpriteFrame","content":{"name":"card25","texture":"b1K5NqJoZLK4CIcSxkOaQF","rect":[240,920,117,151],"offset":[0,0],"originalSize":[117,151]}},{"__type__":"cc.SpriteFrame","content":{"name":"card32","texture":"b1K5NqJoZLK4CIcSxkOaQF","rect":[359,716,117,151],"offset":[0,0],"originalSize":[117,151],"rotated":1}},{"__type__":"cc.SpriteFrame","content":{"name":"card17","texture":"b1K5NqJoZLK4CIcSxkOaQF","rect":[359,1192,117,151],"offset":[0,0],"originalSize":[117,151],"rotated":1}},{"__type__":"cc.SpriteFrame","content":{"name":"card47","texture":"b1K5NqJoZLK4CIcSxkOaQF","rect":[359,121,117,151],"offset":[0,0],"originalSize":[117,151],"rotated":1}},{"__type__":"cc.SpriteFrame","content":{"name":"card39","texture":"b1K5NqJoZLK4CIcSxkOaQF","rect":[121,461,117,151],"offset":[0,0],"originalSize":[117,151]}},{"__type__":"cc.SpriteFrame","content":{"name":"card46","texture":"b1K5NqJoZLK4CIcSxkOaQF","rect":[240,155,117,151],"offset":[0,0],"originalSize":[117,151]}},{"__type__":"cc.SpriteFrame","content":{"name":"card27","texture":"b1K5NqJoZLK4CIcSxkOaQF","rect":[2,1073,117,151],"offset":[0,0],"originalSize":[117,151]}},{"__type__":"cc.SpriteFrame","content":{"name":"card12","texture":"b1K5NqJoZLK4CIcSxkOaQF","rect":[240,1379,117,151],"offset":[0,0],"originalSize":[117,151]}},{"__type__":"cc.SpriteFrame","content":{"name":"card48","texture":"b1K5NqJoZLK4CIcSxkOaQF","rect":[359,2,117,151],"offset":[0,0],"originalSize":[117,151],"rotated":1}},{"__type__":"cc.SpriteFrame","content":{"name":"card26","texture":"b1K5NqJoZLK4CIcSxkOaQF","rect":[121,920,117,151],"offset":[0,0],"originalSize":[117,151]}},{"__type__":"cc.SpriteFrame","content":{"name":"card16","texture":"b1K5NqJoZLK4CIcSxkOaQF","rect":[240,1226,117,151],"offset":[0,0],"originalSize":[117,151]}},{"__type__":"cc.SpriteFrame","content":{"name":"card33","texture":"b1K5NqJoZLK4CIcSxkOaQF","rect":[240,614,117,151],"offset":[0,0],"originalSize":[117,151]}},{"__type__":"cc.SpriteFrame","content":{"name":"card31","texture":"b1K5NqJoZLK4CIcSxkOaQF","rect":[2,920,117,151],"offset":[0,0],"originalSize":[117,151]}},{"__type__":"cc.SpriteFrame","content":{"name":"card13","texture":"b1K5NqJoZLK4CIcSxkOaQF","rect":[121,1379,117,151],"offset":[0,0],"originalSize":[117,151]}},{"__type__":"cc.SpriteFrame","content":{"name":"card22","texture":"b1K5NqJoZLK4CIcSxkOaQF","rect":[121,1073,117,151],"offset":[0,0],"originalSize":[117,151]}},{"__type__":"cc.SpriteFrame","content":{"name":"card36","texture":"b1K5NqJoZLK4CIcSxkOaQF","rect":[359,597,117,151],"offset":[0,0],"originalSize":[117,151],"rotated":1}},{"__type__":"cc.SpriteFrame","content":{"name":"card34","texture":"b1K5NqJoZLK4CIcSxkOaQF","rect":[121,614,117,151],"offset":[0,0],"originalSize":[117,151]}},{"__type__":"cc.SpriteFrame","content":{"name":"card28","texture":"b1K5NqJoZLK4CIcSxkOaQF","rect":[359,835,117,151],"offset":[0,0],"originalSize":[117,151],"rotated":1}},{"__type__":"cc.SpriteFrame","content":{"name":"card00_new","texture":"46BH8GbcVIO7chIbULojOw","rect":[0,0,117,151],"offset":[0,0],"originalSize":[117,151]}},{"__type__":"cc.SpriteFrame","content":{"name":"card03","texture":"b1K5NqJoZLK4CIcSxkOaQF","rect":[240,1685,117,151],"offset":[0,0],"originalSize":[117,151]}},{"__type__":"cc.SpriteFrame","content":{"name":"card44","texture":"b1K5NqJoZLK4CIcSxkOaQF","rect":[2,461,117,151],"offset":[0,0],"originalSize":[117,151]}},{"__type__":"cc.SpriteFrame","content":{"name":"card40","texture":"b1K5NqJoZLK4CIcSxkOaQF","rect":[2,614,117,151],"offset":[0,0],"originalSize":[117,151]}},{"__type__":"cc.SpriteFrame","content":{"name":"card35","texture":"b1K5NqJoZLK4CIcSxkOaQF","rect":[2,767,117,151],"offset":[0,0],"originalSize":[117,151]}},{"__type__":"cc.SpriteFrame","content":{"name":"card52","texture":"b1K5NqJoZLK4CIcSxkOaQF","rect":[121,2,117,151],"offset":[0,0],"originalSize":[117,151]}},{"__type__":"cc.SpriteFrame","content":{"name":"card21","texture":"b1K5NqJoZLK4CIcSxkOaQF","rect":[2,1379,117,151],"offset":[0,0],"originalSize":[117,151]}},{"__type__":"cc.SpriteFrame","content":{"name":"card15","texture":"b1K5NqJoZLK4CIcSxkOaQF","rect":[359,1311,117,151],"offset":[0,0],"originalSize":[117,151],"rotated":1}},{"__type__":"cc.SpriteFrame","content":{"name":"card51","texture":"b1K5NqJoZLK4CIcSxkOaQF","rect":[2,308,117,151],"offset":[0,0],"originalSize":[117,151]}}]